ontologist/__init__.py
ontologist/entrypoints.py
ontologist/models.py
ontologist/retrievers.py
ontologist/rules.py
ontologist/utils.py
ontologist/validators.py
ontologist-0.2.0.dist-info/LICENSE
ontologist-0.2.0.dist-info/METADATA
ontologist-0.2.0.dist-info/WHEEL
ontologist-0.2.0.dist-info/RECORD
