Metadata-Version: 2.1
Name: ontologist
Version: 0.2.0
Summary: A Python library for validating RDF data alignment with ontologies without requiring shape resources.
Home-page: https://github.com/atomobianco/ontologist
Author: Tommaso Bianco
Author-email: tommaso.bianco@gmail.com
Requires-Python: >=3.9,<4.0
Classifier: Programming Language :: Python :: 3
Classifier: Programming Language :: Python :: 3.9
Classifier: Programming Language :: Python :: 3.10
Classifier: Programming Language :: Python :: 3.11
Classifier: Programming Language :: Python :: 3.12
Requires-Dist: rdflib (>=7.0.0,<8.0.0)
Project-URL: Repository, https://github.com/atomobianco/ontologist
